onestop/__init__.py
onestop/consumer.py
onestop/producer.py
onestop_python_client_cedardevs-0.2.5.dist-info/LICENSE
onestop_python_client_cedardevs-0.2.5.dist-info/METADATA
onestop_python_client_cedardevs-0.2.5.dist-info/WHEEL
onestop_python_client_cedardevs-0.2.5.dist-info/top_level.txt
onestop_python_client_cedardevs-0.2.5.dist-info/RECORD
