Metadata-Version: 2.1
Name: onestop-python-client-cedardevs
Version: 0.2.5
Summary: A python package for processing messages from the NOAA OneStop event stream (aka Inventory Manager).
Home-page: https://github.com/cedardevs/onestop-clients
Author: CEDARDEVS
Author-email: cedar.cires@colorado.edu
License: UNKNOWN
Platform: UNKNOWN
Classifier: Programming Language :: Python :: 3
Classifier: License :: OSI Approved :: MIT License
Classifier: Operating System :: OS Independent
Requires-Python: >=3.6
